aws_helpers/__init__.py
aws_helpers/version.py
aws_helpers/s3.py
aws_helpers/client.py
aws_helpers/test/test_client.py
aws_helpers/test/__init__.py
aws_helpers/test/test_s3.py
aws_helpers-0.61.dist-info/DESCRIPTION.rst
aws_helpers-0.61.dist-info/metadata.json
aws_helpers-0.61.dist-info/RECORD
aws_helpers-0.61.dist-info/METADATA
aws_helpers-0.61.dist-info/top_level.txt
aws_helpers-0.61.dist-info/WHEEL
