Metadata-Version: 2.0
Name: aws-helpers
Version: 0.61
Summary: Some helpers for working with boto3.
Home-page: https://github.com/ps-george/aws_helpers
Author: George Punter
Author-email: puntersg@gmail.com
License: MIT
Platform: UNKNOWN
Classifier: License :: OSI Approved :: MIT License
Classifier: Programming Language :: Python
Classifier: Programming Language :: Python :: 3
Classifier: Programming Language :: Python :: 3.6
Classifier: Programming Language :: Python :: Implementation :: CPython
Classifier: Programming Language :: Python :: Implementation :: PyPy
Requires-Dist: boto3
